civitai_models_manager/__init__.py
civitai_models_manager/__main__.py
civitai_models_manager/__version__.py
civitai_models_manager/cli.py
civitai_models_manager/modules/__init__.py
civitai_models_manager/modules/ai.py
civitai_models_manager/modules/create.py
civitai_models_manager/modules/details.py
civitai_models_manager/modules/download.py
civitai_models_manager/modules/helpers.py
civitai_models_manager/modules/list.py
civitai_models_manager/modules/remove.py
civitai_models_manager/modules/search.py
civitai_models_manager/modules/stats.py
civitai_models_manager/modules/tools.py
civitai_models_manager/modules/utils.py
civitai_models_manager-0.8.6.dist-info/METADATA
civitai_models_manager-0.8.6.dist-info/WHEEL
civitai_models_manager-0.8.6.dist-info/entry_points.txt
civitai_models_manager-0.8.6.dist-info/licenses/LICENSE
civitai_models_manager-0.8.6.dist-info/RECORD
