Metadata-Version: 2.4
Name: civitai_models_manager
Version: 0.8.6
Summary: CLI tool for managing AI models from the CivitAI platform.
Project-URL: Repository, https://github.com/regiellis/civitai-cli-manager
Project-URL: Documentation, https://github.com/regiellis/civitai-cli-manager/blob/main/README.md
Project-URL: Bug Tracker, https://github.com/regiellis/civitai-cli-manager/issues
Author-email: Regi E <regi@bynine.io>
License: Copyright 2024 Regi E Ellis
License-File: LICENSE
Keywords: ai,artificial intelligence,civitai,cli,machine learning,manager,ml,model
Classifier: License :: OSI Approved :: Apache Software License
Classifier: Operating System :: OS Independent
Classifier: Programming Language :: Python :: 3.9
Requires-Python: <=3.13,>=3.9
Requires-Dist: asyncio
Requires-Dist: civitai-py
Requires-Dist: groq
Requires-Dist: html2text
Requires-Dist: httpx
Requires-Dist: ollama
Requires-Dist: openai
Requires-Dist: python-dotenv
Requires-Dist: questionary
Requires-Dist: rich
Requires-Dist: shellingham
Requires-Dist: tenacity
Requires-Dist: typer
